{"type": "FeatureCollection", "features": [{"geometry": {"type": "Point", "coordinates": [-95.3422334, 29.7199489]}, "type": "Feature", "properties": {"photos": [{"height": 2988, "photo_reference": "CoQBdwAAAJC95PNmruOauJ4Rmrg9iqFSa1hqq43k5SIaf4OFikcSwK2g79vvxNeeyYOSLsKWxgj9IpBdDgy3LAYTjhiQrQdbqQNI23NW5wqJSFwmDreccVkSxo3jpIqcVRixppKaJkxtoMGquggJkrtrAqj_wBf2PvOQ7eRg4uVcCywJ6jnpEhAyxkDkD1NnKug8SnNtG0oBGhRx0SXPvRYsJrsTKjec57JqLTCtFw", "width": 5312, "html_attributions": ["<a href=\"https://maps.google.com/maps/contrib/112933440860029710314/photos\">Abhishek kaurav</a>"]}], "id": "f7ec825bef7fdab2793f8eff2019cde9a0c3ba13", "types": ["university", "point_of_interest", "establishment"], "reference": "CmRRAAAAvXQfw3vuPeSQwfmNP9fhoN2T0cKrYh35i7uP0J1HhQglrYP8jkUwBJL8wf2cIYZjzLd110Rl29rBLxtyv5AWwA0VpZPrPiav5iImp-OhdBCpd3VF3dgOm_UCoOWoRB-1EhBIM5gMX7jGgeXYWP2Fy4e5GhTvRmKv4Gy-EJ6wC2DZikPQqUdmXQ", "name": "University of Houston", "address": "4800 Calhoun Rd, Houston, TX 77004, United States", "place_id": "ChIJmaG-jlq-QIYR50eCyn44nww", "rating": 4.4}}]}